no_cloud/__init__.py
no_cloud/__main__.py
no_cloud/cli.py
no_cloud/crypto.py
no_cloud/formatter.py
no_cloud/fs.py
no_cloud/utils.py
no_cloud/remote/__init__.py
no_cloud/remote/base.py
no_cloud/remote/minio.py
no_cloud/remote/s3.py
no_cloud-0.0.8.data/data/assets/stylesheet.css
no_cloud-0.0.8.dist-info/DESCRIPTION.rst
no_cloud-0.0.8.dist-info/METADATA
no_cloud-0.0.8.dist-info/RECORD
no_cloud-0.0.8.dist-info/WHEEL
no_cloud-0.0.8.dist-info/entry_points.txt
no_cloud-0.0.8.dist-info/metadata.json
no_cloud-0.0.8.dist-info/top_level.txt
