Metadata-Version: 2.0
Name: no-cloud
Version: 0.0.8
Summary: There is no cloud
Home-page: http://github.com/saalaa/no-cloud
Author: Benoit Myard
Author-email: myardbenoit@gmail.com
License: BSD
Platform: any
Classifier: Topic :: Utilities
Classifier: Environment :: Console
Classifier: Intended Audience :: Developers
Classifier: License :: OSI Approved :: BSD License
Classifier: Programming Language :: Python
Classifier: Programming Language :: Python :: 2
Classifier: Programming Language :: Python :: 3
Requires-Dist: CairoSVG (==1.0.22)
Requires-Dist: Markdown (==2.6.7)
Requires-Dist: PyYAML (==3.12)
Requires-Dist: Pyphen (==0.9.4)
Requires-Dist: WeasyPrint (==0.34)
Requires-Dist: boto3 (==1.4.4)
Requires-Dist: botocore (==1.5.24)
Requires-Dist: cairocffi (==0.7.2)
Requires-Dist: cffi (==1.9.1)
Requires-Dist: click (==6.6)
Requires-Dist: cryptography (==1.7.1)
Requires-Dist: cssselect (==1.0.0)
Requires-Dist: docutils (==0.13.1)
Requires-Dist: enum34 (==1.1.6)
Requires-Dist: html5lib (==0.999999999)
Requires-Dist: idna (==2.2)
Requires-Dist: ipaddress (==1.0.17)
Requires-Dist: jmespath (==0.9.2)
Requires-Dist: lxml (==3.7.1)
Requires-Dist: pyasn1 (==0.1.9)
Requires-Dist: pycparser (==2.17)
Requires-Dist: pyperclip (==1.5.27)
Requires-Dist: s3transfer (==0.1.10)
Requires-Dist: six (==1.10.0)
Requires-Dist: tinycss (==0.4)
Requires-Dist: webencodings (==0.5)
